setup.py
src/digimat/__init__.py
src/digimat.remoteblock.egg-info/PKG-INFO
src/digimat.remoteblock.egg-info/SOURCES.txt
src/digimat.remoteblock.egg-info/dependency_links.txt
src/digimat.remoteblock.egg-info/namespace_packages.txt
src/digimat.remoteblock.egg-info/not-zip-safe
src/digimat.remoteblock.egg-info/requires.txt
src/digimat.remoteblock.egg-info/top_level.txt
src/digimat/remoteblock/__init__.py
src/digimat/remoteblock/remoteblock.py