Metadata-Version: 1.0
Name: digimat.remoteblock
Version: 0.0.2
Summary: Digimat CPU RemoteBlock
Home-page: UNKNOWN
Author: Frederic Hess
Author-email: fhess@splust.ch
License: PSF
Platform: UNKNOWN
